uipath_connectors/oracle_netsuite/__init__.py
uipath_connectors/oracle_netsuite/client.py
uipath_connectors/oracle_netsuite/errors.py
uipath_connectors/oracle_netsuite/py.typed
uipath_connectors/oracle_netsuite/types.py
uipath_connectors/oracle_netsuite/api/__init__.py
uipath_connectors/oracle_netsuite/api/curated_contact/__init__.py
uipath_connectors/oracle_netsuite/api/curated_contact/create_basic_contact.py
uipath_connectors/oracle_netsuite/api/curated_customer/__init__.py
uipath_connectors/oracle_netsuite/api/curated_customer/create_customer.py
uipath_connectors/oracle_netsuite/api/curated_customer/update_customer.py
uipath_connectors/oracle_netsuite/api/curated_support_case/__init__.py
uipath_connectors/oracle_netsuite/api/curated_support_case/create_supportcase.py
uipath_connectors/oracle_netsuite/api/curated_update_contact/__init__.py
uipath_connectors/oracle_netsuite/api/curated_update_contact/update_basic_contact.py
uipath_connectors/oracle_netsuite/api/curated_update_support_case/__init__.py
uipath_connectors/oracle_netsuite/api/curated_update_support_case/update_supportcase.py
uipath_connectors/oracle_netsuite/api/curated_vendor/__init__.py
uipath_connectors/oracle_netsuite/api/curated_vendor/create_vendor.py
uipath_connectors/oracle_netsuite/api/curated_vendor/update_vendor.py
uipath_connectors/oracle_netsuite/api/execute_suite_ql/__init__.py
uipath_connectors/oracle_netsuite/api/execute_suite_ql/execute_suite_ql_query.py
uipath_connectors/oracle_netsuite/api/file_download/__init__.py
uipath_connectors/oracle_netsuite/api/file_download/download_file.py
uipath_connectors/oracle_netsuite/api/search_customers/__init__.py
uipath_connectors/oracle_netsuite/api/search_customers/search_customers.py
uipath_connectors/oracle_netsuite/api/search_inventory_item/__init__.py
uipath_connectors/oracle_netsuite/api/search_inventory_item/search_items.py
uipath_connectors/oracle_netsuite/models/__init__.py
uipath_connectors_oracle_netsuite-1.4.7.dev12.dist-info/METADATA
uipath_connectors_oracle_netsuite-1.4.7.dev12.dist-info/WHEEL
uipath_connectors_oracle_netsuite-1.4.7.dev12.dist-info/entry_points.txt
uipath_connectors_oracle_netsuite-1.4.7.dev12.dist-info/top_level.txt
uipath_connectors_oracle_netsuite-1.4.7.dev12.dist-info/RECORD
